gpuinfonv/__init__.py
gpuinfonv/gpu_info.py
gpuinfonv/gpu_stat.py
gpuinfonv-0.1.0.dist-info/METADATA
gpuinfonv-0.1.0.dist-info/WHEEL
gpuinfonv-0.1.0.dist-info/RECORD
