Metadata-Version: 2.1
Name: gpuinfonv
Version: 0.1.0
Summary: A Python library for gathering and managing information about NVIDIA GPUs
Home-page: https://github.com/soumendra/gpuinfo
License: MIT
Keywords: gpu,nvidia,cuda,pytorch
Author: Soumendra Dhanee
Author-email: soumendra@gmail.com
Requires-Python: >=3.10,<4.0
Classifier: License :: OSI Approved :: MIT License
Classifier: Programming Language :: Python :: 3
Classifier: Programming Language :: Python :: 3.10
Classifier: Programming Language :: Python :: 3.11
Classifier: Programming Language :: Python :: 3.12
Requires-Dist: psutil (>=6.0.0,<7.0.0)
Requires-Dist: pydantic (>=2.8.2,<3.0.0)
Requires-Dist: pynvml (>=11.5.3,<12.0.0)
Project-URL: Documentation, https://soumendra.github.io/gpuinfo/
Project-URL: Repository, https://github.com/soumendra/gpuinfo
